ipy_list_explorer/__init__.py
ipy_list_explorer/widget.py
ipy_list_explorer-0.0.2.dist-info/METADATA
ipy_list_explorer-0.0.2.dist-info/WHEEL
ipy_list_explorer-0.0.2.dist-info/licenses/LICENSE
ipy_list_explorer-0.0.2.dist-info/RECORD
