Metadata-Version: 2.4
Name: ipy_list_explorer
Version: 0.0.2
Summary: A simple list explorer package for ipython contexts
Project-URL: Homepage, https://github.com/danielmccannsayles/ipy-list-explorer
Project-URL: Repository, https://github.com/danielmccannsayles/ipy-list-explorer
Author-email: Daniel McCann-Sayles <danielmccannsayles@gmail.com>
License-Expression: MIT
License-File: LICENSE
Keywords: explorer,ipython,ipywidgets,jupyter,list,list explorer,preview
Classifier: Intended Audience :: Developers
Classifier: Operating System :: OS Independent
Classifier: Programming Language :: Python :: 3
Requires-Python: >=3.9
Requires-Dist: ipython>=7.0.0
Requires-Dist: ipywidgets>=7.0.0
